Metadata-Version: 2.1
Name: meracan-s3netcdf
Version: 0.0.2
Summary: Create partition netcdf files on s3
Home-page: https://github.com/meracan/s3-netcdf
Author: Julien Cousineau
Author-email: Julien.Cousineau@gmail.com
License: MIT
Platform: UNKNOWN
Classifier: Programming Language :: Python :: 3
Classifier: License :: OSI Approved :: MIT License
Classifier: Operating System :: OS Independent
Requires-Python: >=3.6
